crispy_bulma/__init__.py
crispy_bulma/bulma.py
crispy_bulma/forms.py
crispy_bulma/layout.py
crispy_bulma/widgets.py
crispy_bulma/templates/bulma/display_form.html
crispy_bulma/templates/bulma/errors.html
crispy_bulma/templates/bulma/field.html
crispy_bulma/templates/bulma/inputs.html
crispy_bulma/templates/bulma/uni_form.html
crispy_bulma/templates/bulma/whole_uni_form.html
crispy_bulma/templates/bulma/layout/baseinput.html
crispy_bulma/templates/bulma/layout/button.html
crispy_bulma/templates/bulma/layout/checkboxinput.html
crispy_bulma/templates/bulma/layout/checkboxselectmultiple.html
crispy_bulma/templates/bulma/layout/checkboxselectmultiple_inline.html
crispy_bulma/templates/bulma/layout/div.html
crispy_bulma/templates/bulma/layout/field_errors.html
crispy_bulma/templates/bulma/layout/field_errors_block.html
crispy_bulma/templates/bulma/layout/formgroup.html
crispy_bulma/templates/bulma/layout/help_text.html
crispy_bulma/templates/bulma/layout/input_with_icon.html
crispy_bulma/templates/bulma/layout/radioselect.html
crispy_bulma/templates/bulma/layout/radioselect_inline.html
crispy_bulma/templates/bulma/layout/select.html
crispy_bulma/templates/bulma/widgets/file_upload_input.html
crispy_bulma/templatetags/__init__.py
crispy_bulma/templatetags/crispy_forms_bulma_field.py
crispy_bulma-0.11.0.dist-info/LICENSE
crispy_bulma-0.11.0.dist-info/METADATA
crispy_bulma-0.11.0.dist-info/WHEEL
crispy_bulma-0.11.0.dist-info/top_level.txt
crispy_bulma-0.11.0.dist-info/RECORD
