Metadata-Version: 2.1
Name: crispy-bulma
Version: 0.11.0
Summary: Bulma template pack for django-crispy-forms
Home-page: https://github.com/ckrybus/crispy-bulma
Author: Christoph Krybus
Author-email: chris@ckrybus.com
License: MIT
Project-URL: Documentation, https://crispy-bulma.readthedocs.io/en/latest/
Project-URL: Source, https://github.com/ckrybus/crispy-bulma
Project-URL: Changelog, https://github.com/ckrybus/crispy-bulma/blob/main/HISTORY.rst
Keywords: forms,django,crispy,bulma
Classifier: Development Status :: 4 - Beta
Classifier: Environment :: Web Environment
Classifier: Framework :: Django
Classifier: Framework :: Django :: 4.2
Classifier: Framework :: Django :: 5.0
Classifier: Intended Audience :: Developers
Classifier: License :: OSI Approved :: MIT License
Classifier: Operating System :: OS Independent
Classifier: Programming Language :: Python
Classifier: Programming Language :: Python :: 3
Classifier: Programming Language :: Python :: 3.8
Classifier: Programming Language :: Python :: 3.9
Classifier: Programming Language :: Python :: 3.10
Classifier: Programming Language :: Python :: 3.11
Classifier: Programming Language :: Python :: 3.12
Classifier: Topic :: Internet :: WWW/HTTP
Classifier: Topic :: Internet :: WWW/HTTP :: Dynamic Content
Classifier: Topic :: Software Development :: Libraries :: Python Modules
Requires-Python: >=3.8
Provides-Extra: test
License-File: LICENSE
